README.md
setup.py
tkitMarker_bert/__init__.py
tkitMarker_bert/marker.py
tkitMarker_bert.egg-info/PKG-INFO
tkitMarker_bert.egg-info/SOURCES.txt
tkitMarker_bert.egg-info/dependency_links.txt
tkitMarker_bert.egg-info/requires.txt
tkitMarker_bert.egg-info/top_level.txt