Metadata-Version: 2.1
Name: tkitMarker-bert
Version: 0.0.0.7
Summary: Terry toolkit
Home-page: https://github.com/napoler/tkitMarker_bert
Author: Terry Chan
Author-email: napoler2008@gmail.com
License: UNKNOWN
Platform: UNKNOWN
